SeleniumLibraryExtends/__init__.py
SeleniumLibraryExtends/highlight.py
SeleniumLibraryExtends/report.py
SeleniumLibraryExtends/version.py
SeleniumLibraryExtends/ElementInteraction/__init__.py
SeleniumLibraryExtends/ElementInteraction/elementInteraction.py
SeleniumLibraryExtends/FindElements/__init__.py
SeleniumLibraryExtends/FindElements/findElements.py
SeleniumLibraryExtends/Navigation/__init__.py
SeleniumLibraryExtends/Navigation/navigation.py
robotframework_seleniumlibraryextends-1.0.0.dist-info/LICENSE.md
robotframework_seleniumlibraryextends-1.0.0.dist-info/METADATA
robotframework_seleniumlibraryextends-1.0.0.dist-info/WHEEL
robotframework_seleniumlibraryextends-1.0.0.dist-info/top_level.txt
robotframework_seleniumlibraryextends-1.0.0.dist-info/RECORD
