Metadata-Version: 2.1
Name: robotframework-seleniumlibraryextends
Version: 1.0.0
Summary: Selenium Library Extension for new keywords
Home-page: https://github.com/dbspt/SeleniumLibraryExtends.git
Author: Cléverson Sampaio
Author-email: cleverson@sampaio.dev.br
Classifier: Development Status :: 5 - Production/Stable
Classifier: Programming Language :: Python
Classifier: Programming Language :: Python :: 3
Classifier: Operating System :: OS Independent
Classifier: Topic :: Software Development :: Testing
Classifier: Framework :: Robot Framework
Classifier: Framework :: Robot Framework :: Library
License-File: LICENSE.md
Requires-Dist: robotframework-seleniumlibrary (>=6.0.0)
